README.txt
setup.py
statprof.py
statprof.egg-info/PKG-INFO
statprof.egg-info/SOURCES.txt
statprof.egg-info/dependency_links.txt
statprof.egg-info/top_level.txt