Metadata-Version: 1.0
Name: statprof
Version: 0.1.2
Summary: Statistical profiling for Python
Home-page: http://packages.python.org/statprof
Author: Bryan O'Sullivan
Author-email: bos@serpentine.com
License: LGPL
Keywords: profiling
Platform: UNKNOWN
Classifier: Development Status :: 3 - Alpha
Classifier: Topic :: Utilities
Classifier: License :: OSI Approved :: GNU Library or Lesser General Public License (LGPL)
